django_kmuhelper-1.8.7.dist-info/licenses/LICENSE
kmuhelper/__init__.py
kmuhelper/admin.py
kmuhelper/apps.py
kmuhelper/constants.py
kmuhelper/decorators.py
kmuhelper/models.py
kmuhelper/overrides.py
kmuhelper/settings.py
kmuhelper/startup.py
kmuhelper/translations.py
kmuhelper/urls.py
kmuhelper/utils.py
kmuhelper/views.py
kmuhelper/widgets.py
kmuhelper/external/__init__.py
kmuhelper/external/multi_email_field/LICENSE
kmuhelper/external/multi_email_field/README.md
kmuhelper/external/multi_email_field/__init__.py
kmuhelper/external/multi_email_field/fields.py
kmuhelper/external/multi_email_field/forms.py
kmuhelper/external/multi_email_field/models.py
kmuhelper/external/multi_email_field/widgets.py
kmuhelper/locale/__qr_invoice_texts.json
kmuhelper/locale/de/LC_MESSAGES/django.mo
kmuhelper/locale/de/LC_MESSAGES/django.po
kmuhelper/locale/en/LC_MESSAGES/django.mo
kmuhelper/locale/en/LC_MESSAGES/django.po
kmuhelper/locale/fr/LC_MESSAGES/django.mo
kmuhelper/locale/fr/LC_MESSAGES/django.po
kmuhelper/locale/it/LC_MESSAGES/django.mo
kmuhelper/locale/it/LC_MESSAGES/django.po
kmuhelper/management/commands/kmuhelper-import-customers.py
kmuhelper/management/commands/model2csv.py
kmuhelper/migrations/0101_squashed_0100_to_0100.py
kmuhelper/migrations/0102_paymentreceiver_improvements.py
kmuhelper/migrations/0103_paymentreceiver_invoice_display_mode.py
kmuhelper/migrations/0104_order_payment_purpose.py
kmuhelper/migrations/0105_alter_setting_options_alter_settinghidden_options.py
kmuhelper/migrations/0106_alter_app_arrival_options_and_more.py
kmuhelper/migrations/0107_alter_emailtemplate_mail_subject_and_more.py
kmuhelper/migrations/0108_migrate_vat_rates_for_2024.py
kmuhelper/migrations/0109_contactperson_is_default_paymentreceiver_is_default.py
kmuhelper/migrations/0110_orderitem_made_product_optional.py
kmuhelper/migrations/0111_alter_order_tracking_number.py
kmuhelper/migrations/0112_product_parent.py
kmuhelper/migrations/0113_customer_woocommerce_deleted_and_more.py
django_kmuhelper-1.8.7.dist-info/METADATA
django_kmuhelper-1.8.7.dist-info/WHEEL
django_kmuhelper-1.8.7.dist-info/top_level.txt
django_kmuhelper-1.8.7.dist-info/RECORD
