Metadata-Version: 2.4
Name: django-kmuhelper
Version: 1.8.7
Summary: Ein Helfer für schweizer KMU
Author-email: Rafael Urben <github@rafaelurben.ch>
Maintainer-email: Rafael Urben <github@rafaelurben.ch>
License-Expression: MIT
Project-URL: Homepage, https://rafaelurben.github.io/django-kmuhelper
Project-URL: Docs, https://rafaelurben.github.io/django-kmuhelper
Project-URL: GitHub, https://github.com/rafaelurben/django-kmuhelper
Project-URL: Issues, https://github.com/rafaelurben/django-kmuhelper/issues
Classifier: Environment :: Web Environment
Classifier: Framework :: Django
Classifier: Framework :: Django :: 5.2
Classifier: Framework :: Django :: 6.0
Classifier: Intended Audience :: Developers
Classifier: Operating System :: OS Independent
Classifier: Programming Language :: Python
Classifier: Programming Language :: Python :: 3
Classifier: Programming Language :: Python :: 3 :: Only
Classifier: Programming Language :: Python :: 3.12
Classifier: Programming Language :: Python :: 3.13
Classifier: Programming Language :: Python :: 3.14
Classifier: Topic :: Internet :: WWW/HTTP
Classifier: Topic :: Internet :: WWW/HTTP :: Dynamic Content
Requires-Python: >=3.12
License-File: LICENSE
Requires-Dist: Django<6.1.0,>=5.2.0
Requires-Dist: requests>=2.26.0
Requires-Dist: WooCommerce<4,>=3.0.0
Requires-Dist: reportlab<5,>=4.3.1
Requires-Dist: rich>=10.15.2
Requires-Dist: packaging>=21.3
Requires-Dist: defusedxml>=0.7.1
Dynamic: license-file
